openworlds/__init__.py
openworlds-0.1.0.dist-info/licenses/LICENSE
openworlds-0.1.0.dist-info/METADATA
openworlds-0.1.0.dist-info/WHEEL
openworlds-0.1.0.dist-info/top_level.txt
openworlds-0.1.0.dist-info/RECORD
